arg/__init__.py
arg/infer.py
arg/train.py
arg/utils.py
arg/data/__init__.py
arg/data/anotate.py
arg/data/build.py
arg/data/preprocess.py
arg/model/BaseModel.py
arg/model/RGGRU.py
arg/model/RGGRUAT.py
arg/model/RGRoFormer.py
arg/model/RGTR.py
arg/model/__init__.py
automated_rhythm_generation-0.0.1.dist-info/METADATA
automated_rhythm_generation-0.0.1.dist-info/WHEEL
automated_rhythm_generation-0.0.1.dist-info/licenses/LICENSE
automated_rhythm_generation-0.0.1.dist-info/RECORD
